openxdf/__init__.py
openxdf/__version__.py
openxdf/exceptions.py
openxdf/helpers.py
openxdf/pretty.py
openxdf/signal.py
openxdf/xdf.py
openxdf-0.5.1.dist-info/METADATA
openxdf-0.5.1.dist-info/RECORD
openxdf-0.5.1.dist-info/WHEEL
openxdf-0.5.1.dist-info/entry_points.txt
openxdf-0.5.1.dist-info/top_level.txt
tests/__init__.py
tests/context.py
tests/test_exceptions.py
tests/test_helpers.py
tests/test_signal.py
tests/test_xdf.py
