Metadata-Version: 2.1
Name: openxdf
Version: 0.5.1
Summary: OpenXDF is a Python module built for interacting with Open eXchange Data Format files.
Home-page: https://github.com/opelr/openxdf
Author: Ryan Opel
Author-email: ryan.a.opel@gmail.com
License: GNU GENERAL PUBLIC LICENSE
Requires-Dist: xmltodict
Requires-Dist: pandas
